simular_evm-0.3.0.dist-info/METADATA
simular_evm-0.3.0.dist-info/WHEEL
simular_evm-0.3.0.dist-info/licenses/LICENSE
simular/contract.py
simular/simular.pyi
simular/utils.py
simular/__init__.py
simular/simular.cp311-win_amd64.pyd
simular_evm-0.3.0.dist-info/RECORD
