Metadata-Version: 2.3
Name: simular-evm
Version: 0.3.0
Classifier: Programming Language :: Python
Classifier: Programming Language :: Python :: 3.10
Classifier: Programming Language :: Python :: 3.11
Classifier: Programming Language :: Rust
Classifier: Programming Language :: Python :: Implementation :: CPython
Classifier: Programming Language :: Python :: Implementation :: PyPy
Requires-Dist: eth-abi >=4.1.0
Requires-Dist: eth-utils >=2.2.0
License-File: LICENSE
Summary: smart-contract api and embedded ethereum virtual machine
Keywords: agent-based modeling,ethereum,solidity,simulation
Home-Page: https://github.com/simular-fi/simular
Author: Dave Bryson
Author-email: Dave Bryson <davebryson@users.noreply.github.com>
License: Apache-2.0
Requires-Python: >=3.10, <3.12
Project-URL: homepage, https://github.com/simular-fi/simular
Project-URL: repository, https://github.com/simular-fi/simular
Project-URL: documentation, https://simular.readthedocs.io/en/latest/
Project-URL: issues, https://github.com/simular-fi/simular/issues
